cla/__init__.py
cla/__main__.py
cla/chat.py
classistant-1.0.4.dist-info/licenses/LICENSE
classistant-1.0.4.dist-info/METADATA
classistant-1.0.4.dist-info/WHEEL
classistant-1.0.4.dist-info/entry_points.txt
classistant-1.0.4.dist-info/top_level.txt
classistant-1.0.4.dist-info/RECORD
