Metadata-Version: 2.4
Name: classistant
Version: 1.0.4
Summary: Command Line AI Assistant
Author: Paulo Lira
License: MIT
Requires-Python: >=3.9
License-File: LICENSE
Requires-Dist: httpx
Dynamic: license-file
